i2c_decoder.v
// =============================================================================
// Module  : i2c_decoder
// Purpose : Decodes I2C bus (SCL + SDA) and extracts:
//             - 7-bit slave address
//             - R/W bit
//             - 8-bit data byte(s)
//             - ACK/NACK from slave
//             - Valid pulse when a complete address/data byte is captured
//
// I2C Protocol Overview:
//   START  : SDA falls while SCL is HIGH
//   STOP   : SDA rises  while SCL is HIGH
//   DATA   : Sampled on rising edge of SCL (MSB first)
//   ACK    : Pulled LOW by the receiver on the 9th clock after 8 data bits
// =============================================================================

module i2c_decoder (
    input  wire       clk,          // System clock (used for edge detection)
    input  wire       rst_n,        // Active-low synchronous reset
    input  wire       scl,          // I2C clock line
    input  wire       sda,          // I2C data  line

    // ---- Decoded outputs ----
    output reg  [6:0] addr,         // 7-bit slave address
    output reg        rw,           // 1 = Read, 0 = Write
    output reg  [7:0] data_byte,    // Latest captured data byte
    output reg        addr_valid,   // Pulsed 1 cycle when address + R/W ready
    output reg        data_valid,   // Pulsed 1 cycle when data byte ready
    output reg        ack,          // ACK bit captured after each byte
    output reg        busy,         // HIGH while a transaction is in progress
    output reg        error         // HIGH if unexpected condition detected
);

    // -----------------------------------------------------------------------
    // Synchronise SCL/SDA into the system clock domain (2-FF synchroniser)
    // -----------------------------------------------------------------------
    reg scl_r1, scl_r2, scl_r3;
    reg sda_r1, sda_r2, sda_r3;

    always @(posedge clk or negedge rst_n) begin
        if (!rst_n) begin
            scl_r1 <= 1'b1; scl_r2 <= 1'b1; scl_r3 <= 1'b1;
            sda_r1 <= 1'b1; sda_r2 <= 1'b1; sda_r3 <= 1'b1;
        end else begin
            scl_r1 <= scl;  scl_r2 <= scl_r1;  scl_r3 <= scl_r2;
            sda_r1 <= sda;  sda_r2 <= sda_r1;  sda_r3 <= sda_r2;
        end
    end

    // Stable (debounced) versions
    wire scl_stable = scl_r2;
    wire sda_stable = sda_r2;

    // Edge detection on stable signals
    wire scl_rising  = ( scl_r2 & ~scl_r3);
    wire scl_falling = (~scl_r2 &  scl_r3);
    wire sda_rising  = ( sda_r2 & ~sda_r3);
    wire sda_falling = (~sda_r2 &  sda_r3);

    // -----------------------------------------------------------------------
    // START/STOP detection
    //   START : SDA falls while SCL is HIGH
    //   STOP  : SDA rises  while SCL is HIGH
    // -----------------------------------------------------------------------
    wire start_det = sda_falling & scl_stable;
    wire stop_det  = sda_rising  & scl_stable;

    // -----------------------------------------------------------------------
    // FSM state encoding
    // -----------------------------------------------------------------------
    localparam [2:0]
        S_IDLE      = 3'd0,   // Waiting for START
        S_ADDR      = 3'd1,   // Receiving 7-bit address
        S_RW        = 3'd2,   // Receiving R/W bit
        S_ACK_ADDR  = 3'd3,   // ACK after address byte
        S_DATA      = 3'd4,   // Receiving 8-bit data
        S_ACK_DATA  = 3'd5;   // ACK after data byte

    reg [2:0] state;
    reg [3:0] bit_cnt;        // Counts bits within a phase (0-7)
    reg [7:0] shift_reg;      // Shift register for incoming bits

    // -----------------------------------------------------------------------
    // FSM
    // -----------------------------------------------------------------------
    always @(posedge clk or negedge rst_n) begin
        if (!rst_n) begin
            state      <= S_IDLE;
            bit_cnt    <= 4'd0;
            shift_reg  <= 8'd0;
            addr       <= 7'd0;
            rw         <= 1'b0;
            data_byte  <= 8'd0;
            addr_valid <= 1'b0;
            data_valid <= 1'b0;
            ack        <= 1'b0;
            busy       <= 1'b0;
            error      <= 1'b0;
        end else begin
            // Default pulse clears
            addr_valid <= 1'b0;
            data_valid <= 1'b0;
            error      <= 1'b0;

            // STOP always returns to IDLE regardless of current state
            if (stop_det) begin
                state <= S_IDLE;
                busy  <= 1'b0;
            end
            // Repeated START: restart from address phase
            else if (start_det) begin
                state     <= S_ADDR;
                bit_cnt   <= 4'd0;
                shift_reg <= 8'd0;
                busy      <= 1'b1;
            end
            else begin
                case (state)
                    // ------------------------------------------
                    S_IDLE: begin
                        busy <= 1'b0;
                        // Stays here until start_det handled above
                    end

                    // ------------------------------------------
                    // Sample bits on SCL rising edge
                    // ------------------------------------------
                    S_ADDR: begin
                        if (scl_rising) begin
                            shift_reg <= {shift_reg[6:0], sda_stable};
                            if (bit_cnt == 4'd6) begin
                                addr    <= {shift_reg[5:0], sda_stable};
                                bit_cnt <= 4'd0;
                                state   <= S_RW;
                            end else begin
                                bit_cnt <= bit_cnt + 1'b1;
                            end
                        end
                    end

                    // ------------------------------------------
                    S_RW: begin
                        if (scl_rising) begin
                            rw         <= sda_stable;
                            addr_valid <= 1'b1;       // Address + R/W captured
                            bit_cnt    <= 4'd0;
                            state      <= S_ACK_ADDR;
                        end
                    end

                    // ------------------------------------------
                    S_ACK_ADDR: begin
                        if (scl_rising) begin
                            ack   <= ~sda_stable;     // ACK = SDA LOW
                            if (sda_stable == 1'b0) begin
                                // ACK received → move to data phase
                                shift_reg <= 8'd0;
                                bit_cnt   <= 4'd0;
                                state     <= S_DATA;
                            end else begin
                                // NACK → flag error, wait for STOP/START
                                error <= 1'b1;
                                state <= S_IDLE;
                            end
                        end
                    end

                    // ------------------------------------------
                    S_DATA: begin
                        if (scl_rising) begin
                            shift_reg <= {shift_reg[6:0], sda_stable};
                            if (bit_cnt == 4'd7) begin
                                data_byte  <= {shift_reg[6:0], sda_stable};
                                data_valid <= 1'b1;
                                bit_cnt    <= 4'd0;
                                state      <= S_ACK_DATA;
                            end else begin
                                bit_cnt <= bit_cnt + 1'b1;
                            end
                        end
                    end

                    // ------------------------------------------
                    S_ACK_DATA: begin
                        if (scl_rising) begin
                            ack <= ~sda_stable;
                            // Regardless of ACK/NACK continue to next byte
                            // (Master may NACK the last byte before STOP)
                            shift_reg <= 8'd0;
                            bit_cnt   <= 4'd0;
                            state     <= S_DATA;
                        end
                    end

                    default: state <= S_IDLE;
                endcase
            end
        end
    end

endmodule

i2c_decoder_tb.v
// =============================================================================
// Testbench : i2c_decoder_tb
// Purpose   : Verifies the i2c_decoder module by driving real I2C sequences:
//               Test 1 - WRITE transaction (addr=0x4A, data=0xA5, 0x3C)
//               Test 2 - READ  transaction (addr=0x4A)
//               Test 3 - Repeated START
//               Test 4 - NACK from slave (error flag expected)
// =============================================================================

`timescale 1ns/1ps

module i2c_decoder_tb;

    // -----------------------------------------------------------------------
    // Parameters
    // -----------------------------------------------------------------------
    // System clock period (100 MHz → 10 ns)
    localparam CLK_PERIOD  = 10;

    // I2C timing in system-clock cycles
    // Standard-mode I2C = 100 kHz → period = 10 µs = 1000 sys clocks
    // Using a much shorter cycle here to keep simulation quick.
    localparam I2C_HALF    = 50;   // Half I2C clock period (cycles)
    localparam I2C_SETUP   = 5;    // SDA setup time before SCL edge (cycles)

    // -----------------------------------------------------------------------
    // DUT signals
    // -----------------------------------------------------------------------
    reg        clk;
    reg        rst_n;
    reg        scl;
    reg        sda;

    wire [6:0] addr;
    wire       rw;
    wire [7:0] data_byte;
    wire       addr_valid;
    wire       data_valid;
    wire       ack;
    wire       busy;
    wire       error;

    // -----------------------------------------------------------------------
    // DUT instantiation
    // -----------------------------------------------------------------------
    i2c_decoder uut (
        .clk        (clk),
        .rst_n      (rst_n),
        .scl        (scl),
        .sda        (sda),
        .addr       (addr),
        .rw         (rw),
        .data_byte  (data_byte),
        .addr_valid (addr_valid),
        .data_valid (data_valid),
        .ack        (ack),
        .busy       (busy),
        .error      (error)
    );

    // -----------------------------------------------------------------------
    // Clock generation
    // -----------------------------------------------------------------------
    initial clk = 1'b0;
    always  #(CLK_PERIOD/2) clk = ~clk;

    // -----------------------------------------------------------------------
    // Utility tasks
    // -----------------------------------------------------------------------

    // Wait N system clocks
    task wait_clocks;
        input integer n;
        integer i;
        begin
            for (i = 0; i < n; i = i + 1)
                @(posedge clk);
        end
    endtask

    // I2C START condition: SDA falls while SCL is HIGH
    task i2c_start;
        begin
            sda = 1'b1;
            scl = 1'b1;
            wait_clocks(I2C_HALF);
            sda = 1'b0;           // SDA falls
            wait_clocks(I2C_HALF);
            scl = 1'b0;           // SCL falls → prepare for first bit
            wait_clocks(I2C_SETUP);
        end
    endtask

    // I2C STOP condition: SDA rises while SCL is HIGH
    task i2c_stop;
        begin
            sda = 1'b0;
            wait_clocks(I2C_SETUP);
            scl = 1'b1;
            wait_clocks(I2C_HALF);
            sda = 1'b1;           // SDA rises
            wait_clocks(I2C_HALF);
        end
    endtask

    // Send one bit (MSB or LSB, caller's choice)
    task i2c_send_bit;
        input bit_val;
        begin
            sda = bit_val;
            wait_clocks(I2C_SETUP);
            scl = 1'b1;                    // SCL rises → DUT samples SDA
            wait_clocks(I2C_HALF);
            scl = 1'b0;                    // SCL falls
            wait_clocks(I2C_SETUP);
        end
    endtask

    // Send one full byte, MSB first; then clock one ACK/NACK cycle.
    // `slave_ack` = 1 → slave sends ACK (SDA=0)
    //             = 0 → slave sends NACK (SDA=1)
    task i2c_send_byte;
        input [7:0] data;
        input       slave_ack;
        integer     i;
        begin
            for (i = 7; i >= 0; i = i - 1)
                i2c_send_bit(data[i]);

            // ACK/NACK phase: SDA driven by slave (modelled here)
            sda = ~slave_ack;             // ACK → SDA=0, NACK → SDA=1
            wait_clocks(I2C_SETUP);
            scl = 1'b1;
            wait_clocks(I2C_HALF);
            scl = 1'b0;
            wait_clocks(I2C_SETUP);
            sda = 1'bz;                   // Release bus
        end
    endtask

    // -----------------------------------------------------------------------
    // Result checking helpers
    // -----------------------------------------------------------------------
    integer pass_cnt = 0;
    integer fail_cnt = 0;

    task check;
        input [63:0] got;
        input [63:0] expected;
        input [127:0] label;
        begin
            if (got === expected) begin
                $display("  [PASS] %s : 0x%0h", label, got);
                pass_cnt = pass_cnt + 1;
            end else begin
                $display("  [FAIL] %s : got=0x%0h  expected=0x%0h", label, got, expected);
                fail_cnt = fail_cnt + 1;
            end
        end
    endtask

    // -----------------------------------------------------------------------
    // Latch for single-cycle error pulse
    // -----------------------------------------------------------------------
    reg error_latch;

    task clear_error_latch;
        begin @(posedge clk); error_latch = 1'b0; end
    endtask

    always @(posedge clk or negedge rst_n) begin
        if (!rst_n)
            error_latch <= 1'b0;
        else if (error)
            error_latch <= 1'b1;
    end

    // -----------------------------------------------------------------------
    // Monitor: print every time addr_valid or data_valid pulse
    // -----------------------------------------------------------------------
    always @(posedge clk) begin
        if (addr_valid)
            $display("  [MON] addr_valid: addr=0x%0h  rw=%0b  (@%0t ns)", addr, rw, $time);
        if (data_valid)
            $display("  [MON] data_valid: data=0x%0h  ack=%0b  (@%0t ns)", data_byte, ack, $time);
        if (error)
            $display("  [MON] ERROR detected                           (@%0t ns)", $time);
    end

    // -----------------------------------------------------------------------
    // Stimulus
    // -----------------------------------------------------------------------
    initial begin
        $dumpfile("i2c_decoder_tb.vcd");
        $dumpvars(0, i2c_decoder_tb);

        // Default idle state
        scl   = 1'b1;
        sda   = 1'b1;
        rst_n = 1'b0;
        wait_clocks(4);
        rst_n = 1'b1;
        wait_clocks(4);

        // ==================================================================
        // Test 1: WRITE transaction
        //   START | addr=0x4A | W=0 | ACK | data=0xA5 | ACK | data=0x3C | ACK | STOP
        // ==================================================================
        $display("\n=== Test 1: WRITE  addr=0x4A  data=[0xA5, 0x3C] ===");
        i2c_start;
        i2c_send_byte({7'h4A, 1'b0}, 1'b1);   // address + WRITE + slave ACK
        wait_clocks(2);
        check(addr, 7'h4A, "T1 addr");
        check(rw,   1'b0,  "T1 rw  ");

        i2c_send_byte(8'hA5, 1'b1);            // data byte 1 + slave ACK
        wait_clocks(2);
        check(data_byte, 8'hA5, "T1 data[0]");

        i2c_send_byte(8'h3C, 1'b1);            // data byte 2 + slave ACK
        wait_clocks(2);
        check(data_byte, 8'h3C, "T1 data[1]");

        i2c_stop;
        wait_clocks(10);

        // ==================================================================
        // Test 2: READ transaction
        //   START | addr=0x4A | R=1 | ACK | STOP
        // ==================================================================
        $display("\n=== Test 2: READ   addr=0x4A ===");
        i2c_start;
        i2c_send_byte({7'h4A, 1'b1}, 1'b1);   // address + READ + slave ACK
        wait_clocks(2);
        check(addr, 7'h4A, "T2 addr");
        check(rw,   1'b1,  "T2 rw  ");
        i2c_stop;
        wait_clocks(10);

        // ==================================================================
        // Test 3: Repeated START (no STOP between two sub-transactions)
        //   START | addr=0x12 | W | ACK | RS | addr=0x55 | W | ACK | STOP
        // ==================================================================
        $display("\n=== Test 3: Repeated START ===");
        i2c_start;
        i2c_send_byte({7'h12, 1'b0}, 1'b1);
        wait_clocks(2);
        check(addr, 7'h12, "T3 addr1");

        // Repeated START: bring SDA/SCL high, then do START again
        sda = 1'b1;
        wait_clocks(I2C_HALF);
        scl = 1'b1;
        wait_clocks(I2C_HALF);
        i2c_start;                              // Repeated START

        i2c_send_byte({7'h55, 1'b0}, 1'b1);
        wait_clocks(2);
        check(addr, 7'h55, "T3 addr2 (after repeated START)");
        i2c_stop;
        wait_clocks(10);

        // ==================================================================
        // Test 4: NACK from slave after address → error flag expected
        //   START | addr=0x7F | W=0 | NACK | (idle)
        // ==================================================================
        $display("\n=== Test 4: NACK from slave (error expected) ===");
        clear_error_latch;                      // Reset latch before this test
        i2c_start;
        i2c_send_byte({7'h7F, 1'b0}, 1'b0);   // slave_ack=0 → NACK
        wait_clocks(10);
        check(error_latch, 1'b1, "T4 error flag");
        i2c_stop;
        wait_clocks(10);

        // ==================================================================
        // Summary
        // ==================================================================
        $display("\n======================================");
        $display(" Results: %0d PASSED, %0d FAILED", pass_cnt, fail_cnt);
        $display("======================================\n");

        if (fail_cnt == 0)
            $display("ALL TESTS PASSED");
        else
            $display("SOME TESTS FAILED - check log above");

        $finish;
    end

endmodule

results/I2C/sim/i2c_decoder_tb.vcd
$date
	Fri Mar 27 00:56:46 2026
$end
$version
	Icarus Verilog
$end
$timescale
	1ps
$end
$scope module i2c_decoder_tb $end
$var wire 1 ! rw $end
$var wire 1 " error $end
$var wire 1 # data_valid $end
$var wire 8 $ data_byte [7:0] $end
$var wire 1 % busy $end
$var wire 1 & addr_valid $end
$var wire 7 ' addr [6:0] $end
$var wire 1 ( ack $end
$var parameter 32 ) CLK_PERIOD $end
$var parameter 32 * I2C_HALF $end
$var parameter 32 + I2C_SETUP $end
$var reg 1 , clk $end
$var reg 1 - error_latch $end
$var reg 1 . rst_n $end
$var reg 1 / scl $end
$var reg 1 0 sda $end
$var integer 32 1 fail_cnt [31:0] $end
$var integer 32 2 pass_cnt [31:0] $end
$scope module uut $end
$var wire 1 , clk $end
$var wire 1 . rst_n $end
$var wire 1 / scl $end
$var wire 1 3 scl_falling $end
$var wire 1 4 scl_rising $end
$var wire 1 5 scl_stable $end
$var wire 1 0 sda $end
$var wire 1 6 sda_falling $end
$var wire 1 7 sda_rising $end
$var wire 1 8 sda_stable $end
$var wire 1 9 start_det $end
$var wire 1 : stop_det $end
$var parameter 3 ; S_ACK_ADDR $end
$var parameter 3 < S_ACK_DATA $end
$var parameter 3 = S_ADDR $end
$var parameter 3 > S_DATA $end
$var parameter 3 ? S_IDLE $end
$var parameter 3 @ S_RW $end
$var reg 1 ( ack $end
$var reg 7 A addr [6:0] $end
$var reg 1 & addr_valid $end
$var reg 4 B bit_cnt [3:0] $end
$var reg 1 % busy $end
$var reg 8 C data_byte [7:0] $end
$var reg 1 # data_valid $end
$var reg 1 " error $end
$var reg 1 ! rw $end
$var reg 1 D scl_r1 $end
$var reg 1 E scl_r2 $end
$var reg 1 F scl_r3 $end
$var reg 1 G sda_r1 $end
$var reg 1 H sda_r2 $end
$var reg 1 I sda_r3 $end
$var reg 8 J shift_reg [7:0] $end
$var reg 3 K state [2:0] $end
$upscope $end
$scope task check $end
$var reg 64 L expected [63:0] $end
$var reg 64 M got [63:0] $end
$var reg 128 N label [127:0] $end
$upscope $end
$scope task clear_error_latch $end
$upscope $end
$scope task i2c_send_bit $end
$var reg 1 O bit_val $end
$upscope $end
$scope task i2c_send_byte $end
$var reg 8 P data [7:0] $end
$var reg 1 Q slave_ack $end
$var integer 32 R i [31:0] $end
$upscope $end
$scope task i2c_start $end
$upscope $end
$scope task i2c_stop $end
$upscope $end
$scope task wait_clocks $end
$var integer 32 S i [31:0] $end
$var integer 32 T n [31:0] $end
$upscope $end
$upscope $end
$enddefinitions $end
$comment Show the parameter values. $end
$dumpall
b10 @
b0 ?
b100 >
b1 =
b101 <
b11 ;
b101 +
b110010 *
b1010 )
$end
#0
$dumpvars
b100 T
b0 S
bx R
xQ
bx P
xO
bx N
bx M
bx L
b0 K
b0 J
1I
1H
1G
1F
1E
1D
b0 C
b0 B
b0 A
0:
09
18
07
06
15
04
03
b0 2
b0 1
10
1/
0.
0-
0,
0(
b0 '
0&
0%
b0 $
0#
0"
0!
$end
#5000
b1 S
1,
#10000
0,
#15000
b10 S
1,
#20000
0,
#25000
b11 S
1,
#30000
0,
#35000
1.
b0 S
1,
#40000
0,
#45000
b1 S
1,
#50000
0,
#55000
b10 S
1,
#60000
0,
#65000
b11 S
1,
#70000
0,
#75000
b110010 T
b0 S
1,
#80000
0,
#85000
b1 S
1,
#90000
0,
#95000
b10 S
1,
#100000
0,
#105000
b11 S
1,
#110000
0,
#115000
b100 S
1,
#120000
0,
#125000
b101 S
1,
#130000
0,
#135000
b110 S
1,
#140000
0,
#145000
b111 S
1,
#150000
0,
#155000
b1000 S
1,
#160000
0,
#165000
b1001 S
1,
#170000
0,
#175000
b1010 S
1,
#180000
0,
#185000
b1011 S
1,
#190000
0,
#195000
b1100 S
1,
#200000
0,
#205000
b1101 S
1,
#210000
0,
#215000
b1110 S
1,
#220000
0,
#225000
b1111 S
1,
#230000
0,
#235000
b10000 S
1,
#240000
0,
#245000
b10001 S
1,
#250000
0,
#255000
b10010 S
1,
#260000
0,
#265000
b10011 S
1,
#270000
0,
#275000
b10100 S
1,
#280000
0,
#285000
b10101 S
1,
#290000
0,
#295000
b10110 S
1,
#300000
0,
#305000
b10111 S
1,
#310000
0,
#315000
b11000 S
1,
#320000
0,
#325000
b11001 S
1,
#330000
0,
#335000
b11010 S
1,
#340000
0,
#345000
b11011 S
1,
#350000
0,
#355000
b11100 S
1,
#360000
0,
#365000
b11101 S
1,
#370000
0,
#375000
b11110 S
1,
#380000
0,
#385000
b11111 S
1,
#390000
0,
#395000
b100000 S
1,
#400000
0,
#405000
b100001 S
1,
#410000
0,
#415000
b100010 S
1,
#420000
0,
#425000
b100011 S
1,
#430000
0,
#435000
b100100 S
1,
#440000
0,
#445000
b100101 S
1,
#450000
0,
#455000
b100110 S
1,
#460000
0,
#465000
b100111 S
1,
#470000
0,
#475000
b101000 S
1,
#480000
0,
#485000
b101001 S
1,
#490000
0,
#495000
b101010 S
1,
#500000
0,
#505000
b101011 S
1,
#510000
0,
#515000
b101100 S
1,
#520000
0,
#525000
b101101 S
1,
#530000
0,
#535000
b101110 S
1,
#540000
0,
#545000
b101111 S
1,
#550000
0,
#555000
b110000 S
1,
#560000
0,
#565000
b110001 S
1,
#570000
0,
#575000
0G
00
b0 S
1,
#580000
0,
#585000
19
16
08
0H
b1 S
1,
#590000
0,
#595000
09
06
0I
1%
b1 K
b10 S
1,
#600000
0,
#605000
b11 S
1,
#610000
0,
#615000
b100 S
1,
#620000
0,
#625000
b101 S
1,
#630000
0,
#635000
b110 S
1,
#640000
0,
#645000
b111 S
1,
#650000
0,
#655000
b1000 S
1,
#660000
0,
#665000
b1001 S
1,
#670000
0,
#675000
b1010 S
1,
#680000
0,
#685000
b1011 S
1,
#690000
0,
#695000
b1100 S
1,
#700000
0,
#705000
b1101 S
1,
#710000
0,
#715000
b1110 S
1,
#720000
0,
#725000
b1111 S
1,
#730000
0,
#735000
b10000 S
1,
#740000
0,
#745000
b10001 S
1,
#750000
0,
#755000
b10010 S
1,
#760000
0,
#765000
b10011 S
1,
#770000
0,
#775000
b10100 S
1,
#780000
0,
#785000
b10101 S
1,
#790000
0,
#795000
b10110 S
1,
#800000
0,
#805000
b10111 S
1,
#810000
0,
#815000
b11000 S
1,
#820000
0,
#825000
b11001 S
1,
#830000
0,
#835000
b11010 S
1,
#840000
0,
#845000
b11011 S
1,
#850000
0,
#855000
b11100 S
1,
#860000
0,
#865000
b11101 S
1,
#870000
0,
#875000
b11110 S
1,
#880000
0,
#885000
b11111 S
1,
#890000
0,
#895000
b100000 S
1,
#900000
0,
#905000
b100001 S
1,
#910000
0,
#915000
b100010 S
1,
#920000
0,
#925000
b100011 S
1,
#930000
0,
#935000
b100100 S
1,
#940000
0,
#945000
b100101 S
1,
#950000
0,
#955000
b100110 S
1,
#960000
0,
#965000
b100111 S
1,
#970000
0,
#975000
b101000 S
1,
#980000
0,
#985000
b101001 S
1,
#990000
0,
#995000
b101010 S
1,
#1000000
0,
#1005000
b101011 S
1,
#1010000
0,
#1015000
b101100 S
1,
#1020000
0,
#1025000
b101101 S
1,
#1030000
0,
#1035000
b101110 S
1,
#1040000
0,
#1045000
b101111 S
1,
#1050000
0,
#1055000
b110000 S
1,
#1060000
0,
#1065000
b110001 S
1,
#1070000
0,
#1075000
0D
b101 T
0/
b0 S
1,
#1080000
0,
#1085000
13
05
0E
b1 S
1,
#1090000
0,
#1095000
03
0F
b10 S
1,
#1100000
0,
#1105000
b11 S
1,
#1110000
0,
#1115000
b100 S
1,
#1120000
0,
#1125000
1G
10
1O
b111 R
1Q
b10010100 P
b0 S
1,
#1130000
0,
#1135000
17
18
1H
b1 S
1,
#1140000
0,
#1145000
07
1I
b10 S
1,
#1150000
0,
#1155000
b11 S
1,
#1160000
0,
#1165000
b100 S
1,
#1170000
0,
#1175000
1D
b110010 T
1/
b0 S
1,
#1180000
0,
#1185000
14
15
1E
b1 S
1,
#1190000
0,
#1195000
04
1F
b1 B
b1 J
b10 S
1,
#1200000
0,
#1205000
b11 S
1,
#1210000
0,
#1215000
b100 S
1,
#1220000
0,
#1225000
b101 S
1,
#1230000
0,
#1235000
b110 S
1,
#1240000
0,
#1245000
b111 S
1,
#1250000
0,
#1255000
b1000 S
1,
#1260000
0,
#1265000
b1001 S
1,
#1270000
0,
#1275000
b1010 S
1,
#1280000
0,
#1285000
b1011 S
1,
#1290000
0,
#1295000
b1100 S
1,
#1300000
0,
#1305000
b1101 S
1,
#1310000
0,
#1315000
b1110 S
1,
#1320000
0,
#1325000
b1111 S
1,
#1330000
0,
#1335000
b10000 S
1,
#1340000
0,
#1345000
b10001 S
1,
#1350000
0,
#1355000
b10010 S
1,
#1360000
0,
#1365000
b10011 S
1,
#1370000
0,
#1375000
b10100 S
1,
#1380000
0,
#1385000
b10101 S
1,
#1390000
0,
#1395000
b10110 S
1,
#1400000
0,
#1405000
b10111 S
1,
#1410000
0,
#1415000
b11000 S
1,
#1420000
0,
#1425000
b11001 S
1,
#1430000
0,
#1435000
b11010 S
1,
#1440000
0,
#1445000
b11011 S
1,
#1450000
0,
#1455000
b11100 S
1,
#1460000
0,
#1465000
b11101 S
1,
#1470000
0,
#1475000
b11110 S
1,
#1480000
0,
#1485000
b11111 S
1,
#1490000
0,
#1495000
b100000 S
1,
#1500000
0,
#1505000
b100001 S
1,
#1510000
0,
#1515000
b100010 S
1,
#1520000
0,
#1525000
b100011 S
1,
#1530000
0,
#1535000
b100100 S
1,
#1540000
0,
#1545000
b100101 S
1,
#1550000
0,
#1555000
b100110 S
1,
#1560000
0,
#1565000
b100111 S
1,
#1570000
0,
#1575000
b101000 S
1,
#1580000
0,
#1585000
b101001 S
1,
#1590000
0,
#1595000
b101010 S
1,
#1600000
0,
#1605000
b101011 S
1,
#1610000
0,
#1615000
b101100 S
1,
#1620000
0,
#1625000
b101101 S
1,
#1630000
0,
#1635000
b101110 S
1,
#1640000
0,
#1645000
b101111 S
1,
#1650000
0,
#1655000
b110000 S
1,
#1660000
0,
#1665000
b110001 S
1,
#1670000
0,
#1675000
0D
b101 T
0/
b0 S
1,
#1680000
0,
#1685000
13
05
0E
b1 S
1,
#1690000
0,
#1695000
03
0F
b10 S
1,
#1700000
0,
#1705000
b11 S
1,
#1710000
0,
#1715000
b100 S
1,
#1720000
0,
#1725000
0G
00
0O
b110 R
b0 S
1,
#1730000
0,
#1735000
16
08
0H
b1 S
1,
#1740000
0,
#1745000
06
0I
b10 S
1,
#1750000
0,
#1755000
b11 S
1,
#1760000
0,
#1765000
b100 S
1,
#1770000
0,
#1775000
1D
b110010 T
1/
b0 S
1,
#1780000
0,
#1785000
14
15
1E
b1 S
1,
#1790000
0,
#1795000
04
1F
b10 B
b10 J
b10 S
1,
#1800000
0,
#1805000
b11 S
1,
#1810000
0,
#1815000
b100 S
1,
#1820000
0,
#1825000
b101 S
1,
#1830000
0,
#1835000
b110 S
1,
#1840000
0,
#1845000
b111 S
1,
#1850000
0,
#1855000
b1000 S
1,
#1860000
0,
#1865000
b1001 S
1,
#1870000
0,
#1875000
b1010 S
1,
#1880000
0,
#1885000
b1011 S
1,
#1890000
0,
#1895000
b1100 S
1,
#1900000
0,
#1905000
b1101 S
1,
#1910000
0,
#1915000
b1110 S
1,
#1920000
0,
#1925000
b1111 S
1,
#1930000
0,
#1935000
b10000 S
1,
#1940000
0,
#1945000
b10001 S
1,
#1950000
0,
#1955000
b10010 S
1,
#1960000
0,
#1965000
b10011 S
1,
#1970000
0,
#1975000
b10100 S
1,
#1980000
0,
#1985000
b10101 S
1,
#1990000
0,
#1995000
b10110 S
1,
#2000000
0,
#2005000
b10111 S
1,
#2010000
0,
#2015000
b11000 S
1,
#2020000
0,
#2025000
b11001 S
1,
#2030000
0,
#2035000
b11010 S
1,
#2040000
0,
#2045000
b11011 S
1,
#2050000
0,
#2055000
b11100 S
1,
#2060000
0,
#2065000
b11101 S
1,
#2070000
0,
#2075000
b11110 S
1,
#2080000
0,
#2085000
b11111 S
1,
#2090000
0,
#2095000
b100000 S
1,
#2100000
0,
#2105000
b100001 S
1,
#2110000
0,
#2115000
b100010 S
1,
#2120000
0,
#2125000
b100011 S
1,
#2130000
0,
#2135000
b100100 S
1,
#2140000
0,
#2145000
b100101 S
1,
#2150000
0,
#2155000
b100110 S
1,
#2160000
0,
#2165000
b100111 S
1,
#2170000
0,
#2175000
b101000 S
1,
#2180000
0,
#2185000
b101001 S
1,
#2190000
0,
#2195000
b101010 S
1,
#2200000
0,
#2205000
b101011 S
1,
#2210000
0,
#2215000
b101100 S
1,
#2220000
0,
#2225000
b101101 S
1,
#2230000
0,
#2235000
b101110 S
1,
#2240000
0,
#2245000
b101111 S
1,
#2250000
0,
#2255000
b110000 S
1,
#2260000
0,
#2265000
b110001 S
1,
#2270000
0,
#2275000
0D
b101 T
0/
b0 S
1,
#2280000
0,
#2285000
13
05
0E
b1 S
1,
#2290000
0,
#2295000
03
0F
b10 S
1,
#2300000
0,
#2305000
b11 S
1,
#2310000
0,
#2315000
b100 S
1,
#2320000
0,
#2325000
b101 R
b0 S
1,
#2330000
0,
#2335000
b1 S
1,
#2340000
0,
#2345000
b10 S
1,
#2350000
0,
#2355000
b11 S
1,
#2360000
0,
#2365000
b100 S
1,
#2370000
0,
#2375000
1D
b110010 T
1/
b0 S
1,
#2380000
0,
#2385000
14
15
1E
b1 S
1,
#2390000
0,
#2395000
04
1F
b11 B
b100 J
b10 S
1,
#2400000
0,
#2405000
b11 S
1,
#2410000
0,
#2415000
b100 S
1,
#2420000
0,
#2425000
b101 S
1,
#2430000
0,
#2435000
b110 S
1,
#2440000
0,
#2445000
b111 S
1,
#2450000
0,
#2455000
b1000 S
1,
#2460000
0,
#2465000
b1001 S
1,
#2470000
0,
#2475000
b1010 S
1,
#2480000
0,
#2485000
b1011 S
1,
#2490000
0,
#2495000
b1100 S
1,
#2500000
0,
#2505000
b1101 S
1,
#2510000
0,
#2515000
b1110 S
1,
#2520000
0,
#2525000
b1111 S
1,
#2530000
0,
#2535000
b10000 S
1,
#2540000
0,
#2545000
b10001 S
1,
#2550000
0,
#2555000
b10010 S
1,
#2560000
0,
#2565000
b10011 S
1,
#2570000
0,
#2575000
b10100 S
1,
#2580000
0,
#2585000
b10101 S
1,
#2590000
0,
#2595000
b10110 S
1,
#2600000
0,
#2605000
b10111 S
1,
#2610000
0,
#2615000
b11000 S
1,
#2620000
0,
#2625000
b11001 S
1,
#2630000
0,
#2635000
b11010 S
1,
#2640000
0,
#2645000
b11011 S
1,
#2650000
0,
#2655000
b11100 S
1,
#2660000
0,
#2665000
b11101 S
1,
#2670000
0,
#2675000
b11110 S
1,
#2680000
0,
#2685000
b11111 S
1,
#2690000
0,
#2695000
b100000 S
1,
#2700000
0,
#2705000
b100001 S
1,
#2710000
0,
#2715000
b100010 S
1,
#2720000
0,
#2725000
b100011 S
1,
#2730000
0,
#2735000
b100100 S
1,
#2740000
0,
#2745000
b100101 S
1,
#2750000
0,
#2755000
b100110 S
1,
#2760000
0,
#2765000
b100111 S
1,
#2770000
0,
#2775000
b101000 S
1,
#2780000
0,
#2785000
b101001 S
1,
#2790000
0,
#2795000
b101010 S
1,
#2800000
0,
#2805000
b101011 S
1,
#2810000
0,
#2815000
b101100 S
1,
#2820000
0,
#2825000
b101101 S
1,
#2830000
0,
#2835000
b101110 S
1,
#2840000
0,
#2845000
b101111 S
1,
#2850000
0,
#2855000
b110000 S
1,
#2860000
0,
#2865000
b110001 S
1,
#2870000
0,
#2875000
0D
b101 T
0/
b0 S
1,
#2880000
0,
#2885000
13
05
0E
b1 S
1,
#2890000
0,
#2895000
03
0F
b10 S
1,
#2900000
0,
#2905000
b11 S
1,
#2910000
0,
#2915000
b100 S
1,
#2920000
0,
#2925000
1G
10
1O
b100 R
b0 S
1,
#2930000
0,
#2935000
17
18
1H
b1 S
1,
#2940000
0,
#2945000
07
1I
b10 S
1,
#2950000
0,
#2955000
b11 S
1,
#2960000
0,
#2965000
b100 S
1,
#2970000
0,
#2975000
1D
b110010 T
1/
b0 S
1,
#2980000
0,
#2985000
14
15
1E
b1 S
1,
#2990000
0,
